otel_wrapper/__init__.py
otel_wrapper/builder.py
otel_wrapper/deps_injector.py
otel_wrapper/domain/dto/application_attributes.py
otel_wrapper/domain/services/logs_service.py
otel_wrapper/domain/services/metrics_service.py
otel_wrapper/domain/services/trace_service.py
otel_wrapper/infrastructure/adapters/log_exporter.py
otel_wrapper/infrastructure/adapters/metrics_exporter.py
otel_wrapper/infrastructure/adapters/trace_exporter.py
otel_wrapper/infrastructure/ports/outbound_logs_exporter.py
otel_wrapper/infrastructure/ports/outbound_metrics_exporter.py
otel_wrapper/infrastructure/ports/outbound_trace_exporter.py
otel_wrapper-0.1.2.dist-info/LICENSE
otel_wrapper-0.1.2.dist-info/METADATA
otel_wrapper-0.1.2.dist-info/WHEEL
otel_wrapper-0.1.2.dist-info/RECORD
