Metadata-Version: 2.1
Name: otel-wrapper
Version: 0.1.2
Summary: OpenTelemetry Wrapper to send traces, metrics and logs to my otel-proxy using OTLP Protocol
License: MIT
Author: Ivanildo Barauna
Author-email: ivanildo.jnr@outlook.com
Requires-Python: >=3.9,<4.0
Classifier: License :: OSI Approved :: MIT License
Classifier: Programming Language :: Python :: 3
Classifier: Programming Language :: Python :: 3.9
Classifier: Programming Language :: Python :: 3.10
Classifier: Programming Language :: Python :: 3.11
Requires-Dist: opentelemetry-api (>=1.29.0,<2.0.0)
Requires-Dist: opentelemetry-exporter-otlp (>=1.29.0,<2.0.0)
Requires-Dist: opentelemetry-instrumentation-requests (>=0.50b0,<0.51)
Requires-Dist: opentelemetry-sdk (>=1.29.0,<2.0.0)
Requires-Dist: pydantic (>=2.10.4,<3.0.0)
